bibliotCheckSum/__init__.py
bibliotCheckSum/checkBin.py
bibliotCheckSum-1.0.0.dist-info/LICENCE
bibliotCheckSum-1.0.0.dist-info/METADATA
bibliotCheckSum-1.0.0.dist-info/WHEEL
bibliotCheckSum-1.0.0.dist-info/top_level.txt
bibliotCheckSum-1.0.0.dist-info/RECORD
