Metadata-Version: 2.1
Name: bibliotCheckSum
Version: 1.0.0
Summary: biblioteca para binários
Author: Alison Vitor
Author-email: alissonmarqueshm30@gmail.com
License: MIT License
Keywords: biblioteca checksum binario
License-File: LICENCE
Requires-Dist: random
